fastlimits-0.0.1.dist-info/METADATA
fastlimits-0.0.1.dist-info/WHEEL
fastlimits-0.0.1.dist-info/entry_points.txt
fastlimits-0.0.1.dist-info/licenses/LICENSE
fastlimits/__init__.py
fastlimits/dependencies.py
fastlimits/exceptions.py
fastlimits/functions.py
fastlimits/limiter.py
fastlimits/middleware.py
fastlimits/py.typed
fastlimits/types.py
fastlimits/utils.py
fastlimits-0.0.1.dist-info/RECORD
