Metadata-Version: 2.1
Name: fastlimits
Version: 0.0.1
Summary: FastLimits is a rate-limiter extensions/middleware for FastAPI applications
Author-Email: Sina Ebrahimi <ebrahimisina78@gmail.com>
Classifier: Intended Audience :: Information Technology
Classifier: Intended Audience :: System Administrators
Classifier: Operating System :: OS Independent
Classifier: Programming Language :: Python :: 3
Classifier: Programming Language :: Python
Classifier: Topic :: Internet
Classifier: Topic :: Software Development :: Libraries :: Application Frameworks
Classifier: Topic :: Software Development :: Libraries :: Python Modules
Classifier: Topic :: Software Development :: Libraries
Classifier: Topic :: Software Development
Classifier: Typing :: Typed
Classifier: Development Status :: 4 - Beta
Classifier: Environment :: Web Environment
Classifier: Framework :: AsyncIO
Classifier: Framework :: FastAPI
Classifier: Framework :: Pydantic
Classifier: Framework :: Pydantic :: 1
Classifier: Intended Audience :: Developers
Classifier: License :: OSI Approved :: MIT License
Classifier: Programming Language :: Python :: 3 :: Only
Classifier: Programming Language :: Python :: 3.8
Classifier: Programming Language :: Python :: 3.9
Classifier: Programming Language :: Python :: 3.10
Classifier: Programming Language :: Python :: 3.11
Classifier: Programming Language :: Python :: 3.12
Classifier: Topic :: Internet :: WWW/HTTP :: HTTP Servers
Classifier: Topic :: Internet :: WWW/HTTP
Project-URL: Homepage, https://github.com/astronuttt/fastlimits
Project-URL: Documentation, https://astronuttt.github.io/fastlimits/
Project-URL: Repository, https://github.com/astronuttt/fastlimits
Project-URL: Issues, https://github.com/astronuttt/fastlimits/issues
Requires-Python: >=3.8
Requires-Dist: limits>=3.13.0
Requires-Dist: fastapi<1.0.0,>=0.115.0
Provides-Extra: async-redis
Requires-Dist: limits[async-redis]>=3.13.0; extra == "async-redis"
Provides-Extra: async-memcached
Requires-Dist: limits[async-memcached]>=3.13.0; extra == "async-memcached"
Provides-Extra: async-mongodb
Requires-Dist: limits[async-mongodb]>=3.13.0; extra == "async-mongodb"
Provides-Extra: async-etcd
Requires-Dist: limtis[async-etcd]>=3.13.0; extra == "async-etcd"
